gomea-1.1.0.dist-info/METADATA
gomea-1.1.0.dist-info/WHEEL
gomea-1.1.0.dist-info/LICENSE
gomea/fitness.cp311-win_amd64.pyd
gomea/fitness.cp311-win_amd64.lib
gomea/discrete.cp311-win_amd64.pyd
gomea/discrete.cp311-win_amd64.lib
gomea/real_valued.cp311-win_amd64.pyd
gomea/real_valued.cp311-win_amd64.lib
gomea/linkage.cp311-win_amd64.pyd
gomea/linkage.cp311-win_amd64.lib
gomea/output.cp311-win_amd64.pyd
gomea/output.cp311-win_amd64.lib
gomea/__init__.py
gomea-1.1.0.dist-info/RECORD
