Metadata-Version: 2.1
Name: gomea
Version: 1.1.0
Summary: Library for the use of various variants of the Gene-pool Optimal Mixing Evolutionary Algorithm (GOMEA).
Author-Email: Anton Bouter <Anton.Bouter@cwi.nl>
License: MIT License
Requires-Python: >=3.9
Requires-Dist: numpy>=1.23.0
Requires-Dist: tqdm>=4.65.0
